point_topic_utils/__init__.py
point_topic_utils/config.py
point_topic_utils/get_secrets.py
point_topic_utils/google_sheets.py
point_topic_utils/snowflake_utils.py
point_topic_utils/update_status.py
point_topic_utils/update_upc_status.py
point_topic_utils/db/__init__.py
point_topic_utils/db/mongodb.py
point_topic_utils/db/snowflake.py
point_topic_utils/models/project.py
point_topic_utils-0.1.26.dist-info/METADATA
point_topic_utils-0.1.26.dist-info/WHEEL
point_topic_utils-0.1.26.dist-info/entry_points.txt
point_topic_utils-0.1.26.dist-info/top_level.txt
point_topic_utils-0.1.26.dist-info/RECORD
