Metadata-Version: 2.4
Name: point-topic-utils
Version: 0.1.26
Summary: Utilities for Point Topic projects
Author: Peter Donaghey
Requires-Dist: pymongo>=4.0.0
Requires-Dist: gspread>=6.2.1
Requires-Dist: google-auth>=2.40.1
Requires-Dist: cachetools>=5.0.0
Requires-Dist: requests>=2.32.0
Requires-Dist: pyasn1>=0.4.1
Requires-Dist: pyasn1_modules>=0.4.2
Requires-Dist: rsa>=4.9.1
Requires-Dist: boto3>=1.35.0
Requires-Dist: snowflake-connector-python[pandas]
Requires-Dist: pandas
Provides-Extra: dev
Requires-Dist: pytest>=7.0.0; extra == "dev"
Requires-Dist: black>=22.0.0; extra == "dev"
Requires-Dist: isort>=5.0.0; extra == "dev"
